crypto_checker/__init__.py
crypto_checker/checker.py
crypto_checker-1.0.3.dist-info/METADATA
crypto_checker-1.0.3.dist-info/WHEEL
crypto_checker-1.0.3.dist-info/top_level.txt
crypto_checker-1.0.3.dist-info/RECORD
