Metadata-Version: 2.1
Name: crypto-checker
Version: 1.0.3
Summary: A simple crypto price checker using CoinGecko API
Home-page: https://github.com/0xbichain/crypto-checker
Author: 0xbichain
Author-email: author@mahaka.net
Project-URL: Source, https://github.com/0xbichain/crypto-checker
Classifier: Development Status :: 5 - Production/Stable
Classifier: License :: OSI Approved :: MIT License
Classifier: Programming Language :: Python :: 3
Classifier: Programming Language :: Python :: 3.6
Classifier: Programming Language :: Python :: 3.7
Classifier: Programming Language :: Python :: 3.8
Classifier: Programming Language :: Python :: 3.9
Requires-Python: >=3.6
Requires-Dist: requests
